{"identifier":{"interfaceLanguage":"swift","url":"doc:\/\/com.swallow.documentation.Compute\/documentation\/Compute\/UnsafeMutableRawPointer\/moveInitializeMemory(as:from:count:)"},"sections":[],"hierarchy":{"paths":[["doc:\/\/com.swallow.documentation.Compute\/documentation\/Compute","doc:\/\/com.swallow.documentation.Compute\/documentation\/Compute\/UnsafeMutableRawPointer"]]},"primaryContentSections":[{"declarations":[{"platforms":["macOS"],"languages":["swift"],"tokens":[{"text":"@discardableResult","kind":"attribute"},{"text":" ","kind":"text"},{"text":"func","kind":"keyword"},{"text":" ","kind":"text"},{"kind":"identifier","text":"moveInitializeMemory"},{"kind":"text","text":"<"},{"kind":"genericParameter","text":"T"},{"kind":"text","text":">("},{"kind":"externalParam","text":"as"},{"kind":"text","text":" "},{"text":"type","kind":"internalParam"},{"text":": ","kind":"text"},{"kind":"typeIdentifier","text":"T"},{"text":".Type, ","kind":"text"},{"kind":"externalParam","text":"from"},{"kind":"text","text":" "},{"text":"source","kind":"internalParam"},{"kind":"text","text":": "},{"text":"UnsafeMutablePointer","identifier":"doc:\/\/com.swallow.documentation.Compute\/documentation\/Compute\/UnsafeMutablePointer","preciseIdentifier":"s:Sp","kind":"typeIdentifier"},{"text":"<","kind":"text"},{"text":"T","kind":"typeIdentifier"},{"kind":"text","text":">, "},{"text":"count","kind":"externalParam"},{"kind":"text","text":": "},{"preciseIdentifier":"s:Si","identifier":"doc:\/\/com.swallow.documentation.Compute\/documentation\/Compute\/Int","text":"Int","kind":"typeIdentifier"},{"kind":"text","text":") -> "},{"kind":"typeIdentifier","preciseIdentifier":"s:Sp","text":"UnsafeMutablePointer","identifier":"doc:\/\/com.swallow.documentation.Compute\/documentation\/Compute\/UnsafeMutablePointer"},{"text":"<","kind":"text"},{"text":"T","kind":"typeIdentifier"},{"kind":"text","text":"> "},{"kind":"keyword","text":"where"},{"text":" ","kind":"text"},{"kind":"typeIdentifier","text":"T"},{"kind":"text","text":" : ~Copyable"}]}],"kind":"declarations"},{"kind":"parameters","parameters":[{"name":"type","content":[{"inlineContent":[{"type":"text","text":"The type to bind this memory to."}],"type":"paragraph"}]},{"content":[{"type":"paragraph","inlineContent":[{"type":"text","text":"A pointer to the values to copy. The memory in the region"},{"type":"text","text":" "},{"type":"codeVoice","code":"source..<(source + count)"},{"type":"text","text":" must be initialized to type "},{"code":"T","type":"codeVoice"},{"type":"text","text":"."}]}],"name":"source"},{"name":"count","content":[{"inlineContent":[{"type":"text","text":"The number of copies of "},{"type":"codeVoice","code":"value"},{"type":"text","text":" to copy into memory. "},{"type":"codeVoice","code":"count"},{"text":" ","type":"text"},{"text":"must not be negative.","type":"text"}],"type":"paragraph"}]}]},{"content":[{"text":"Return Value","anchor":"return-value","type":"heading","level":2},{"inlineContent":[{"text":"A typed pointer to the memory referenced by this raw pointer.","type":"text"}],"type":"paragraph"}],"kind":"content"},{"kind":"content","content":[{"level":2,"text":"Discussion","anchor":"discussion","type":"heading"},{"type":"paragraph","inlineContent":[{"type":"text","text":"The memory referenced by this pointer must be uninitialized or"},{"text":" ","type":"text"},{"type":"text","text":"initialized to a trivial type, and must be properly aligned for"},{"type":"text","text":" "},{"type":"text","text":"accessing "},{"type":"codeVoice","code":"T"},{"text":".","type":"text"}]},{"type":"paragraph","inlineContent":[{"text":"The memory in the region ","type":"text"},{"code":"source..<(source + count)","type":"codeVoice"},{"text":" may overlap with the","type":"text"},{"text":" ","type":"text"},{"text":"destination region. The ","type":"text"},{"code":"moveInitializeMemory(as:from:count:)","type":"codeVoice"},{"type":"text","text":" method"},{"type":"text","text":" "},{"text":"automatically performs a forward or backward copy of all instances from","type":"text"},{"text":" ","type":"text"},{"text":"the source region to their destination.","type":"text"}]},{"type":"paragraph","inlineContent":[{"text":"After calling this method on a raw pointer ","type":"text"},{"code":"p","type":"codeVoice"},{"type":"text","text":", the region starting at"},{"type":"text","text":" "},{"type":"codeVoice","code":"p"},{"text":" and continuing up to ","type":"text"},{"type":"codeVoice","code":"p + count * MemoryLayout<T>.stride"},{"type":"text","text":" is bound"},{"text":" ","type":"text"},{"type":"text","text":"to type "},{"code":"T","type":"codeVoice"},{"type":"text","text":" and initialized. If "},{"type":"codeVoice","code":"T"},{"text":" is a nontrivial type, you must","type":"text"},{"type":"text","text":" "},{"type":"text","text":"eventually deinitialize or move from the values in this region to avoid"},{"text":" ","type":"text"},{"text":"leaks. Any memory in the region ","type":"text"},{"code":"source..<(source + count)","type":"codeVoice"},{"text":" that does","type":"text"},{"text":" ","type":"text"},{"type":"text","text":"not overlap with the destination region is returned to an uninitialized"},{"type":"text","text":" "},{"text":"state.","type":"text"}]}]}],"variants":[{"traits":[{"interfaceLanguage":"swift"}],"paths":["\/documentation\/compute\/unsafemutablerawpointer\/moveinitializememory(as:from:count:)"]}],"metadata":{"symbolKind":"method","title":"moveInitializeMemory(as:from:count:)","externalID":"s:Sv20moveInitializeMemory2as4from5countSpyxGxm_AESitRi_zlF","fragments":[{"text":"func","kind":"keyword"},{"kind":"text","text":" "},{"text":"moveInitializeMemory","kind":"identifier"},{"text":"<","kind":"text"},{"text":"T","kind":"genericParameter"},{"kind":"text","text":">("},{"text":"as","kind":"externalParam"},{"kind":"text","text":": "},{"kind":"typeIdentifier","text":"T"},{"text":".Type, ","kind":"text"},{"kind":"externalParam","text":"from"},{"kind":"text","text":": "},{"text":"UnsafeMutablePointer","kind":"typeIdentifier","preciseIdentifier":"s:Sp"},{"kind":"text","text":"<"},{"kind":"typeIdentifier","text":"T"},{"kind":"text","text":">, "},{"kind":"externalParam","text":"count"},{"text":": ","kind":"text"},{"text":"Int","kind":"typeIdentifier","preciseIdentifier":"s:Si"},{"text":") -> ","kind":"text"},{"kind":"typeIdentifier","preciseIdentifier":"s:Sp","text":"UnsafeMutablePointer"},{"text":"<","kind":"text"},{"text":"T","kind":"typeIdentifier"},{"text":">","kind":"text"}],"modules":[{"name":"Compute","relatedModules":["Swift"]}],"roleHeading":"Instance Method","extendedModule":"Swift","role":"symbol"},"kind":"symbol","abstract":[{"text":"Initializes the memory referenced by this pointer with the values","type":"text"},{"type":"text","text":" "},{"type":"text","text":"starting at the given pointer, binds the memory to the values’ type,"},{"type":"text","text":" "},{"type":"text","text":"deinitializes the source memory, and returns a typed pointer to the"},{"text":" ","type":"text"},{"text":"newly initialized memory.","type":"text"}],"schemaVersion":{"patch":0,"major":0,"minor":3},"references":{"doc://com.swallow.documentation.Compute/documentation/Compute/UnsafeMutableRawPointer/moveInitializeMemory(as:from:count:)":{"abstract":[{"text":"Initializes the memory referenced by this pointer with the values","type":"text"},{"text":" ","type":"text"},{"type":"text","text":"starting at the given pointer, binds the memory to the values’ type,"},{"type":"text","text":" "},{"text":"deinitializes the source memory, and returns a typed pointer to the","type":"text"},{"type":"text","text":" "},{"text":"newly initialized memory.","type":"text"}],"role":"symbol","type":"topic","identifier":"doc:\/\/com.swallow.documentation.Compute\/documentation\/Compute\/UnsafeMutableRawPointer\/moveInitializeMemory(as:from:count:)","title":"moveInitializeMemory(as:from:count:)","fragments":[{"text":"func","kind":"keyword"},{"text":" ","kind":"text"},{"kind":"identifier","text":"moveInitializeMemory"},{"kind":"text","text":"<"},{"text":"T","kind":"genericParameter"},{"text":">(","kind":"text"},{"text":"as","kind":"externalParam"},{"text":": ","kind":"text"},{"text":"T","kind":"typeIdentifier"},{"text":".Type, ","kind":"text"},{"kind":"externalParam","text":"from"},{"text":": ","kind":"text"},{"text":"UnsafeMutablePointer","kind":"typeIdentifier","preciseIdentifier":"s:Sp"},{"text":"<","kind":"text"},{"text":"T","kind":"typeIdentifier"},{"kind":"text","text":">, "},{"text":"count","kind":"externalParam"},{"text":": ","kind":"text"},{"preciseIdentifier":"s:Si","kind":"typeIdentifier","text":"Int"},{"kind":"text","text":") -> "},{"kind":"typeIdentifier","text":"UnsafeMutablePointer","preciseIdentifier":"s:Sp"},{"kind":"text","text":"<"},{"text":"T","kind":"typeIdentifier"},{"text":">","kind":"text"}],"url":"\/documentation\/compute\/unsafemutablerawpointer\/moveinitializememory(as:from:count:)","kind":"symbol"},"doc://com.swallow.documentation.Compute/documentation/Compute/UnsafeMutableRawPointer":{"kind":"symbol","type":"topic","abstract":[{"text":"A raw pointer for accessing and manipulating untyped data.","type":"text"}],"identifier":"doc:\/\/com.swallow.documentation.Compute\/documentation\/Compute\/UnsafeMutableRawPointer","url":"\/documentation\/compute\/unsafemutablerawpointer","role":"symbol","fragments":[{"text":"struct","kind":"keyword"},{"text":" ","kind":"text"},{"kind":"identifier","text":"UnsafeMutableRawPointer"}],"title":"UnsafeMutableRawPointer","navigatorTitle":[{"kind":"identifier","text":"UnsafeMutableRawPointer"}]},"doc://com.swallow.documentation.Compute/documentation/Compute/UnsafeMutablePointer":{"identifier":"doc:\/\/com.swallow.documentation.Compute\/documentation\/Compute\/UnsafeMutablePointer","fragments":[{"text":"struct","kind":"keyword"},{"kind":"text","text":" "},{"kind":"identifier","text":"UnsafeMutablePointer"}],"url":"\/documentation\/compute\/unsafemutablepointer","type":"topic","abstract":[{"type":"text","text":"A pointer for accessing and manipulating data of a"},{"text":" ","type":"text"},{"text":"specific type.","type":"text"}],"kind":"symbol","role":"symbol","navigatorTitle":[{"kind":"identifier","text":"UnsafeMutablePointer"}],"title":"UnsafeMutablePointer"},"doc://com.swallow.documentation.Compute/documentation/Compute/Int":{"identifier":"doc:\/\/com.swallow.documentation.Compute\/documentation\/Compute\/Int","abstract":[{"type":"text","text":"A signed integer value type."}],"type":"topic","role":"symbol","fragments":[{"kind":"keyword","text":"struct"},{"text":" ","kind":"text"},{"text":"Int","kind":"identifier"}],"navigatorTitle":[{"text":"Int","kind":"identifier"}],"title":"Int","url":"\/documentation\/compute\/int","kind":"symbol"},"doc://com.swallow.documentation.Compute/documentation/Compute":{"identifier":"doc:\/\/com.swallow.documentation.Compute\/documentation\/Compute","url":"\/documentation\/compute","role":"collection","kind":"symbol","abstract":[],"type":"topic","title":"Compute"}}}