{"sections":[],"kind":"symbol","primaryContentSections":[{"declarations":[{"platforms":["macOS"],"languages":["swift"],"tokens":[{"text":"static","kind":"keyword"},{"text":" ","kind":"text"},{"kind":"keyword","text":"func"},{"text":" ","kind":"text"},{"kind":"identifier","text":"list"},{"kind":"text","text":"<"},{"kind":"genericParameter","text":"MemberStyle"},{"kind":"text","text":", "},{"text":"Base","kind":"genericParameter"},{"kind":"text","text":">("},{"kind":"externalParam","text":"memberStyle"},{"text":": ","kind":"text"},{"kind":"typeIdentifier","text":"MemberStyle"},{"kind":"text","text":", "},{"kind":"externalParam","text":"type"},{"kind":"text","text":": "},{"identifier":"doc:\/\/com.swallow.documentation.FoundationX\/documentation\/FoundationX\/ListFormatStyle","text":"ListFormatStyle","preciseIdentifier":"s:10Foundation15ListFormatStyleV","kind":"typeIdentifier"},{"kind":"text","text":"<"},{"kind":"typeIdentifier","text":"MemberStyle"},{"kind":"text","text":", "},{"kind":"typeIdentifier","text":"Base"},{"text":">.","kind":"text"},{"text":"ListType","kind":"typeIdentifier","preciseIdentifier":"s:10Foundation15ListFormatStyleV0B4TypeO","identifier":"doc:\/\/com.swallow.documentation.FoundationX\/documentation\/FoundationX\/ListFormatStyle\/ListType-swift.enum"},{"text":", ","kind":"text"},{"text":"width","kind":"externalParam"},{"kind":"text","text":": "},{"text":"ListFormatStyle","identifier":"doc:\/\/com.swallow.documentation.FoundationX\/documentation\/FoundationX\/ListFormatStyle","preciseIdentifier":"s:10Foundation15ListFormatStyleV","kind":"typeIdentifier"},{"text":"<","kind":"text"},{"text":"MemberStyle","kind":"typeIdentifier"},{"text":", ","kind":"text"},{"kind":"typeIdentifier","text":"Base"},{"kind":"text","text":">."},{"text":"Width","kind":"typeIdentifier","preciseIdentifier":"s:10Foundation15ListFormatStyleV5WidthO","identifier":"doc:\/\/com.swallow.documentation.FoundationX\/documentation\/FoundationX\/ListFormatStyle\/Width-swift.enum"},{"kind":"text","text":" = .standard) -> "},{"kind":"typeIdentifier","text":"Self"},{"kind":"text","text":" "},{"kind":"keyword","text":"where"},{"text":" ","kind":"text"},{"kind":"typeIdentifier","text":"Self"},{"text":" == ","kind":"text"},{"preciseIdentifier":"s:10Foundation15ListFormatStyleV","identifier":"doc:\/\/com.swallow.documentation.FoundationX\/documentation\/FoundationX\/ListFormatStyle","text":"ListFormatStyle","kind":"typeIdentifier"},{"text":"<","kind":"text"},{"text":"MemberStyle","kind":"typeIdentifier"},{"kind":"text","text":", "},{"text":"Base","kind":"typeIdentifier"},{"text":">, ","kind":"text"},{"text":"MemberStyle","kind":"typeIdentifier"},{"text":" : ","kind":"text"},{"text":"FormatStyle","kind":"typeIdentifier","preciseIdentifier":"s:10Foundation11FormatStyleP","identifier":"doc:\/\/com.swallow.documentation.FoundationX\/documentation\/FoundationX\/FormatStyle"},{"text":", ","kind":"text"},{"text":"Base","kind":"typeIdentifier"},{"kind":"text","text":" : "},{"text":"Sequence","kind":"typeIdentifier","preciseIdentifier":"s:ST"},{"text":", ","kind":"text"},{"text":"MemberStyle","kind":"typeIdentifier"},{"kind":"text","text":"."},{"text":"FormatInput","kind":"typeIdentifier","identifier":"doc:\/\/com.swallow.documentation.FoundationX\/documentation\/FoundationX\/FormatStyle\/FormatInput","preciseIdentifier":"s:10Foundation11FormatStyleP0B5InputQa"},{"kind":"text","text":" == "},{"kind":"typeIdentifier","text":"Base"},{"kind":"text","text":"."},{"kind":"typeIdentifier","preciseIdentifier":"s:ST7ElementQa","text":"Element"},{"text":", ","kind":"text"},{"text":"MemberStyle","kind":"typeIdentifier"},{"text":".","kind":"text"},{"kind":"typeIdentifier","preciseIdentifier":"s:10Foundation11FormatStyleP0B6OutputQa","text":"FormatOutput","identifier":"doc:\/\/com.swallow.documentation.FoundationX\/documentation\/FoundationX\/FormatStyle\/FormatOutput"},{"text":" == ","kind":"text"},{"preciseIdentifier":"s:SS","kind":"typeIdentifier","text":"String"}]}],"kind":"declarations"}],"schemaVersion":{"major":0,"patch":0,"minor":3},"hierarchy":{"paths":[["doc:\/\/com.swallow.documentation.FoundationX\/documentation\/FoundationX","doc:\/\/com.swallow.documentation.FoundationX\/documentation\/FoundationX\/Measurement","doc:\/\/com.swallow.documentation.FoundationX\/documentation\/FoundationX\/Measurement\/FormatStyle","doc:\/\/com.swallow.documentation.FoundationX\/documentation\/FoundationX\/Measurement\/FormatStyle\/ByteCount","doc:\/\/com.swallow.documentation.FoundationX\/documentation\/FoundationX\/Measurement\/FormatStyle\/ByteCount\/FormatStyle-Implementations"]]},"identifier":{"url":"doc:\/\/com.swallow.documentation.FoundationX\/documentation\/FoundationX\/Measurement\/FormatStyle\/ByteCount\/list(memberStyle:type:width:)","interfaceLanguage":"swift"},"metadata":{"symbolKind":"method","fragments":[{"text":"static","kind":"keyword"},{"text":" ","kind":"text"},{"text":"func","kind":"keyword"},{"kind":"text","text":" "},{"text":"list","kind":"identifier"},{"text":"<","kind":"text"},{"kind":"genericParameter","text":"MemberStyle"},{"text":", ","kind":"text"},{"text":"Base","kind":"genericParameter"},{"text":">(","kind":"text"},{"kind":"externalParam","text":"memberStyle"},{"kind":"text","text":": "},{"text":"MemberStyle","kind":"typeIdentifier"},{"kind":"text","text":", "},{"text":"type","kind":"externalParam"},{"text":": ","kind":"text"},{"kind":"typeIdentifier","text":"ListFormatStyle","preciseIdentifier":"s:10Foundation15ListFormatStyleV"},{"kind":"text","text":"<"},{"kind":"typeIdentifier","text":"MemberStyle"},{"text":", ","kind":"text"},{"text":"Base","kind":"typeIdentifier"},{"kind":"text","text":">."},{"preciseIdentifier":"s:10Foundation15ListFormatStyleV0B4TypeO","text":"ListType","kind":"typeIdentifier"},{"text":", ","kind":"text"},{"kind":"externalParam","text":"width"},{"kind":"text","text":": "},{"kind":"typeIdentifier","preciseIdentifier":"s:10Foundation15ListFormatStyleV","text":"ListFormatStyle"},{"kind":"text","text":"<"},{"text":"MemberStyle","kind":"typeIdentifier"},{"text":", ","kind":"text"},{"text":"Base","kind":"typeIdentifier"},{"text":">.","kind":"text"},{"preciseIdentifier":"s:10Foundation15ListFormatStyleV5WidthO","kind":"typeIdentifier","text":"Width"},{"text":") -> ","kind":"text"},{"kind":"typeIdentifier","text":"Self"}],"platforms":[{"unavailable":false,"deprecated":false,"beta":false,"name":"iOS","introducedAt":"15.0"},{"name":"macOS","introducedAt":"12.0","deprecated":false,"unavailable":false,"beta":false},{"introducedAt":"15.0","unavailable":false,"beta":false,"deprecated":false,"name":"tvOS"},{"name":"watchOS","introducedAt":"8.0","deprecated":false,"unavailable":false,"beta":false}],"extendedModule":"Foundation","roleHeading":"Type Method","title":"list(memberStyle:type:width:)","role":"symbol","externalID":"s:10Foundation11FormatStylePAAE4list06memberC04type5widthAA04ListbC0Vyqd__qd_0_Gqd___AI0H4TypeOyqd__qd_0__GAI5WidthOyqd__qd_0__GtAJRszAaBRd__STRd_0_7ElementQyd_0_0B5InputRtd__SS0B6OutputRtd__r0_lFZ::SYNTHESIZED::s:10Foundation11MeasurementVAASo11NSDimensionCRbzrlE11FormatStyleVAASo24NSUnitInformationStorageCRszrlE9ByteCountV","modules":[{"relatedModules":["Foundation"],"name":"FoundationX"}]},"variants":[{"traits":[{"interfaceLanguage":"swift"}],"paths":["\/documentation\/foundationx\/measurement\/formatstyle\/bytecount\/list(memberstyle:type:width:)"]}],"abstract":[{"text":"Inherited from ","type":"text"},{"type":"codeVoice","code":"FormatStyle.list(memberStyle:type:width:)"},{"type":"text","text":"."}],"references":{"doc://com.swallow.documentation.FoundationX/documentation/FoundationX":{"abstract":[],"kind":"symbol","title":"FoundationX","identifier":"doc:\/\/com.swallow.documentation.FoundationX\/documentation\/FoundationX","url":"\/documentation\/foundationx","role":"collection","type":"topic"},"doc://com.swallow.documentation.FoundationX/documentation/FoundationX/Measurement/FormatStyle/ByteCount/list(memberStyle:type:width:)":{"kind":"symbol","abstract":[],"identifier":"doc:\/\/com.swallow.documentation.FoundationX\/documentation\/FoundationX\/Measurement\/FormatStyle\/ByteCount\/list(memberStyle:type:width:)","title":"list(memberStyle:type:width:)","url":"\/documentation\/foundationx\/measurement\/formatstyle\/bytecount\/list(memberstyle:type:width:)","fragments":[{"text":"static","kind":"keyword"},{"text":" ","kind":"text"},{"text":"func","kind":"keyword"},{"kind":"text","text":" "},{"text":"list","kind":"identifier"},{"kind":"text","text":"<"},{"text":"MemberStyle","kind":"genericParameter"},{"kind":"text","text":", "},{"text":"Base","kind":"genericParameter"},{"kind":"text","text":">("},{"text":"memberStyle","kind":"externalParam"},{"kind":"text","text":": "},{"kind":"typeIdentifier","text":"MemberStyle"},{"kind":"text","text":", "},{"kind":"externalParam","text":"type"},{"text":": ","kind":"text"},{"kind":"typeIdentifier","text":"ListFormatStyle","preciseIdentifier":"s:10Foundation15ListFormatStyleV"},{"kind":"text","text":"<"},{"kind":"typeIdentifier","text":"MemberStyle"},{"kind":"text","text":", "},{"kind":"typeIdentifier","text":"Base"},{"text":">.","kind":"text"},{"text":"ListType","kind":"typeIdentifier","preciseIdentifier":"s:10Foundation15ListFormatStyleV0B4TypeO"},{"kind":"text","text":", "},{"text":"width","kind":"externalParam"},{"text":": ","kind":"text"},{"preciseIdentifier":"s:10Foundation15ListFormatStyleV","text":"ListFormatStyle","kind":"typeIdentifier"},{"kind":"text","text":"<"},{"kind":"typeIdentifier","text":"MemberStyle"},{"kind":"text","text":", "},{"text":"Base","kind":"typeIdentifier"},{"kind":"text","text":">."},{"text":"Width","kind":"typeIdentifier","preciseIdentifier":"s:10Foundation15ListFormatStyleV5WidthO"},{"kind":"text","text":") -> "},{"kind":"typeIdentifier","text":"Self"}],"type":"topic","role":"symbol"},"doc://com.swallow.documentation.FoundationX/documentation/FoundationX/Measurement":{"abstract":[{"text":"A ","type":"text"},{"code":"Measurement","type":"codeVoice"},{"type":"text","text":" is a model type that holds a "},{"code":"Double","type":"codeVoice"},{"text":" value associated with a ","type":"text"},{"code":"Unit","type":"codeVoice"},{"text":".","type":"text"}],"kind":"symbol","role":"symbol","title":"Measurement","navigatorTitle":[{"kind":"identifier","text":"Measurement"}],"fragments":[{"text":"struct","kind":"keyword"},{"kind":"text","text":" "},{"text":"Measurement","kind":"identifier"}],"url":"\/documentation\/foundationx\/measurement","type":"topic","identifier":"doc:\/\/com.swallow.documentation.FoundationX\/documentation\/FoundationX\/Measurement"},"doc://com.swallow.documentation.FoundationX/documentation/FoundationX/Measurement/FormatStyle":{"url":"\/documentation\/foundationx\/measurement\/formatstyle","kind":"symbol","role":"symbol","conformance":{"availabilityPrefix":[{"text":"Available when","type":"text"}],"conformancePrefix":[{"text":"Conforms when","type":"text"}],"constraints":[{"code":"UnitType","type":"codeVoice"},{"type":"text","text":" inherits "},{"code":"Dimension","type":"codeVoice"},{"text":".","type":"text"}]},"fragments":[{"text":"struct","kind":"keyword"},{"kind":"text","text":" "},{"text":"FormatStyle","kind":"identifier"}],"identifier":"doc:\/\/com.swallow.documentation.FoundationX\/documentation\/FoundationX\/Measurement\/FormatStyle","navigatorTitle":[{"kind":"identifier","text":"FormatStyle"}],"abstract":[],"type":"topic","title":"Measurement.FormatStyle"},"doc://com.swallow.documentation.FoundationX/documentation/FoundationX/Measurement/FormatStyle/ByteCount":{"kind":"symbol","url":"\/documentation\/foundationx\/measurement\/formatstyle\/bytecount","navigatorTitle":[{"kind":"identifier","text":"ByteCount"}],"abstract":[],"type":"topic","title":"Measurement.FormatStyle.ByteCount","role":"symbol","conformance":{"constraints":[{"code":"UnitType","type":"codeVoice"},{"type":"text","text":" is "},{"type":"codeVoice","code":"UnitInformationStorage"},{"text":".","type":"text"}],"conformancePrefix":[{"text":"Conforms when","type":"text"}],"availabilityPrefix":[{"text":"Available when","type":"text"}]},"identifier":"doc:\/\/com.swallow.documentation.FoundationX\/documentation\/FoundationX\/Measurement\/FormatStyle\/ByteCount","fragments":[{"kind":"keyword","text":"struct"},{"text":" ","kind":"text"},{"text":"ByteCount","kind":"identifier"}]},"doc://com.swallow.documentation.FoundationX/documentation/FoundationX/FormatStyle":{"role":"symbol","fragments":[{"kind":"keyword","text":"protocol"},{"kind":"text","text":" "},{"text":"FormatStyle","kind":"identifier"}],"type":"topic","title":"FormatStyle","url":"\/documentation\/foundationx\/formatstyle","kind":"symbol","navigatorTitle":[{"kind":"identifier","text":"FormatStyle"}],"identifier":"doc:\/\/com.swallow.documentation.FoundationX\/documentation\/FoundationX\/FormatStyle","abstract":[{"text":"A type that can convert a given data type into a representation.","type":"text"}]},"doc://com.swallow.documentation.FoundationX/documentation/FoundationX/FormatStyle/FormatInput":{"type":"topic","kind":"symbol","required":true,"title":"FormatInput","fragments":[{"kind":"keyword","text":"associatedtype"},{"text":" ","kind":"text"},{"kind":"identifier","text":"FormatInput"}],"identifier":"doc:\/\/com.swallow.documentation.FoundationX\/documentation\/FoundationX\/FormatStyle\/FormatInput","abstract":[{"text":"The type of data to format.","type":"text"}],"url":"\/documentation\/foundationx\/formatstyle\/formatinput","role":"symbol"},"doc://com.swallow.documentation.FoundationX/documentation/FoundationX/FormatStyle/FormatOutput":{"type":"topic","kind":"symbol","required":true,"title":"FormatOutput","fragments":[{"text":"associatedtype","kind":"keyword"},{"kind":"text","text":" "},{"kind":"identifier","text":"FormatOutput"}],"identifier":"doc:\/\/com.swallow.documentation.FoundationX\/documentation\/FoundationX\/FormatStyle\/FormatOutput","abstract":[{"text":"The type of the formatted data.","type":"text"}],"url":"\/documentation\/foundationx\/formatstyle\/formatoutput","role":"symbol"},"doc://com.swallow.documentation.FoundationX/documentation/FoundationX/ListFormatStyle/Width-swift.enum":{"url":"\/documentation\/foundationx\/listformatstyle\/width-swift.enum","role":"symbol","identifier":"doc:\/\/com.swallow.documentation.FoundationX\/documentation\/FoundationX\/ListFormatStyle\/Width-swift.enum","abstract":[],"fragments":[{"text":"enum","kind":"keyword"},{"kind":"text","text":" "},{"kind":"identifier","text":"Width"}],"kind":"symbol","title":"ListFormatStyle.Width","navigatorTitle":[{"kind":"identifier","text":"Width"}],"type":"topic"},"doc://com.swallow.documentation.FoundationX/documentation/FoundationX/ListFormatStyle/ListType-swift.enum":{"url":"\/documentation\/foundationx\/listformatstyle\/listtype-swift.enum","type":"topic","role":"symbol","fragments":[{"text":"enum","kind":"keyword"},{"text":" ","kind":"text"},{"kind":"identifier","text":"ListType"}],"kind":"symbol","navigatorTitle":[{"kind":"identifier","text":"ListType"}],"identifier":"doc:\/\/com.swallow.documentation.FoundationX\/documentation\/FoundationX\/ListFormatStyle\/ListType-swift.enum","abstract":[],"title":"ListFormatStyle.ListType"},"doc://com.swallow.documentation.FoundationX/documentation/FoundationX/Measurement/FormatStyle/ByteCount/FormatStyle-Implementations":{"type":"topic","abstract":[],"url":"\/documentation\/foundationx\/measurement\/formatstyle\/bytecount\/formatstyle-implementations","kind":"article","role":"collectionGroup","identifier":"doc:\/\/com.swallow.documentation.FoundationX\/documentation\/FoundationX\/Measurement\/FormatStyle\/ByteCount\/FormatStyle-Implementations","title":"FormatStyle Implementations"},"doc://com.swallow.documentation.FoundationX/documentation/FoundationX/ListFormatStyle":{"url":"\/documentation\/foundationx\/listformatstyle","title":"ListFormatStyle","type":"topic","role":"symbol","identifier":"doc:\/\/com.swallow.documentation.FoundationX\/documentation\/FoundationX\/ListFormatStyle","fragments":[{"kind":"keyword","text":"struct"},{"text":" ","kind":"text"},{"text":"ListFormatStyle","kind":"identifier"}],"kind":"symbol","navigatorTitle":[{"text":"ListFormatStyle","kind":"identifier"}],"abstract":[]}}}